metakernel/__init__.py
metakernel/_metakernel.py
metakernel/config.py
metakernel/display.py
metakernel/magic.py
metakernel/parser.py
metakernel/pexpect.py
metakernel/process_metakernel.py
metakernel/replwrap.py
metakernel/images/dragon.py
metakernel/images/logo-32x32.png
metakernel/images/logo-512x512.png
metakernel/images/logo-64x64.png
metakernel/magics/README.md
metakernel/magics/__init__.py
metakernel/magics/activity_magic.py
metakernel/magics/blockly_magic.py
metakernel/magics/brain_magic.py
metakernel/magics/cd_magic.py
metakernel/magics/connect_info_magic.py
metakernel/magics/conversation_magic.py
metakernel/magics/debug_magic.py
metakernel/magics/dot_magic.py
metakernel/magics/download_magic.py
metakernel/magics/edit_magic.py
metakernel/magics/file_magic.py
metakernel/magics/get_magic.py
metakernel/magics/help_magic.py
metakernel/magics/html_magic.py
metakernel/magics/include_magic.py
metakernel/magics/install_magic.py
metakernel/magics/install_magic_magic.py
metakernel/magics/javascript_magic.py
metakernel/magics/jigsaw_magic.py
metakernel/magics/kernel_magic.py
metakernel/magics/latex_magic.py
metakernel/magics/load_magic.py
metakernel/magics/ls_magic.py
metakernel/magics/lsmagic_magic.py
metakernel/magics/macro_magic.py
metakernel/magics/magic_magic.py
metakernel/magics/matplotlib_magic.py
metakernel/magics/parallel_magic.py
metakernel/magics/pipe_magic.py
metakernel/magics/plot_magic.py
metakernel/magics/processing_magic.py
metakernel/magics/python_magic.py
metakernel/magics/reload_magics_magic.py
metakernel/magics/restart_magic.py
metakernel/magics/run_magic.py
metakernel/magics/scheme_magic.py
metakernel/magics/set_magic.py
metakernel/magics/shell_magic.py
metakernel/magics/show_magic.py
metakernel/magics/time_magic.py
metakernel/magics/tutor_magic.py
metakernel/magics/tests/__init__.py
metakernel/magics/tests/test_cd_magic.py
metakernel/magics/tests/test_connect_info_magic.py
metakernel/magics/tests/test_debug_magic.py
metakernel-0.30.4.dist-info/METADATA
metakernel-0.30.4.dist-info/WHEEL
metakernel-0.30.4.dist-info/licenses/LICENSE.txt
metakernel-0.30.4.dist-info/RECORD
