Metadata-Version: 2.4
Name: metakernel
Version: 0.30.4
Dynamic: Summary
Project-URL: Homepage, https://github.com/Calysto/metakernel
Author-email: Metakernel Developers <steven.silvester@ieee.org>
License-File: LICENSE.txt
Classifier: Framework :: IPython
Classifier: Intended Audience :: Developers
Classifier: License :: OSI Approved :: BSD License
Classifier: Programming Language :: Python :: 3
Classifier: Topic :: System :: Shells
Requires-Python: >=3.9
Requires-Dist: ipykernel>=5.5.6
Requires-Dist: jedi>=0.18
Requires-Dist: jupyter-core>=4.9.2
Requires-Dist: pexpect>=4.8
Provides-Extra: activity
Requires-Dist: portalocker; extra == 'activity'
Provides-Extra: parallel
Requires-Dist: ipyparallel; extra == 'parallel'
Provides-Extra: test
Requires-Dist: jupyter-kernel-test; extra == 'test'
Requires-Dist: pytest; extra == 'test'
Requires-Dist: pytest-cov; extra == 'test'
Requires-Dist: pytest-timeout; extra == 'test'
Requires-Dist: requests; extra == 'test'
